CB11002UNO/__init__.py
CB11002UNO/lineales.py
CB11002UNO/no_lineales.py
cb11002uno-0.1.0.dist-info/METADATA
cb11002uno-0.1.0.dist-info/WHEEL
cb11002uno-0.1.0.dist-info/top_level.txt
cb11002uno-0.1.0.dist-info/RECORD
