Metadata-Version: 2.4
Name: CB11002UNO
Version: 0.1.0
Summary: Librería de métodos numéricos para sistemas de ecuaciones lineales y no lineales
Home-page: https://github.com/josepb38/CB11002UNO
Author: Josep
Author-email: cb11002@ues.edu.sv
Classifier: Programming Language :: Python :: 3
Classifier: License :: OSI Approved :: MIT License
Classifier: Operating System :: OS Independent
Requires-Python: >=3.6
Requires-Dist: numpy
Requires-Dist: scipy
Dynamic: author
Dynamic: author-email
Dynamic: classifier
Dynamic: home-page
Dynamic: requires-dist
Dynamic: requires-python
Dynamic: summary
